<?xml version="1.0" encoding="UTF-8"?>

<!DOCTYPE struts PUBLIC
        "-//Apache Software Foundation//DTD Struts Configuration 2.5//EN"
        "http://struts.apache.org/dtds/struts-2.5.dtd">


<struts>

    <package name="user" namespace="/" extends="struts-default,json-default">

        <global-results >
            <result type="json" name="json"></result>
        </global-results>

        <action name="readitem" class="action.StoreAction" method="readitem">
            <result name="success">/storelist.jsp</result>
            <result name="error">/index.jsp</result>
        </action>


        <action name="itemadd" class="action.StoreAction" method="itemadd">
            <result name="success">/itemadd1.jsp</result>
            <result name="error">/itemadd.jsp</result>

        </action>

        <action name="itemcorr" class="action.StoreAction" method="itemcorr">
            <result name="success">/itemcorr1.jsp</result>
        </action>


        <action name="itemdelete" class="action.StoreAction" method="itemdelete">
            <result name="success">/delete1.jsp</result>
            <result name="error">/index.jsp</result>
        </action>

        <action name="validation" class="action.StoreAction" method="validation">
        </action>

        <action name="rereadItem" method="rereadItem" class="action.StoreAction">
        <result name="success">storelist.jsp</result>
        <result name="error">index.jsp</result>
        </action>

    </package>
</struts>